{"assets":{"672EE0C5DB726A7305A298BBDB9D6824":{"type":"texture","index":5,"assetRequest":{"type":"slide","state":"contents","slide":"none"},"url":{"native":"assets\/57D59BF8-900B-4C0A-9E93-9B19486BB94C.pdf"},"width":1421,"height":41},"73746CC77F98038CCDD6A664DF9DC261":{"type":"texture","index":8,"assetRequest":{"type":"slide","state":"contents","slide":"none"},"url":{"native":"assets\/57D59BF8-900B-4C0A-9E93-9B19486BB94C.pdf"},"width":1059,"height":41},"769346EB9B7D226C18A37CD23110C7E0":{"type":"texture","index":1,"assetRequest":{"type":"slide","state":"contents","slide":"none"},"url":{"native":"assets\/57D59BF8-900B-4C0A-9E93-9B19486BB94C.pdf"},"width":1005,"height":115},"1E00397D677FE47D00B9009AE78DD3DF":{"type":"texture","index":4,"assetRequest":{"type":"slide","state":"contents","slide":"none"},"url":{"native":"assets\/57D59BF8-900B-4C0A-9E93-9B19486BB94C.pdf"},"width":153,"height":153},"D30DCBD739CF9BA010D281948BDF9250":{"type":"texture","index":3,"assetRequest":{"type":"slide","state":"contents","slide":"none"},"url":{"native":"assets\/57D59BF8-900B-4C0A-9E93-9B19486BB94C.pdf"},"width":1586,"height":115},"C25C25FF361FB24FC35F6B120D2F252D":{"type":"texture","index":0,"assetRequest":{"type":"slide","state":"contents","slide":"none"},"url":{"native":"assets\/57D59BF8-900B-4C0A-9E93-9B19486BB94C.pdf"},"width":1920,"height":1080},"17D5F579A7EEF91B82F8F0BDFB2BB53B":{"type":"texture","index":6,"assetRequest":{"type":"slide","state":"contents","slide":"none"},"url":{"native":"assets\/57D59BF8-900B-4C0A-9E93-9B19486BB94C.pdf"},"width":1206,"height":115},"304E32496D30F9D769E87A3F923D691F":{"type":"texture","index":7,"assetRequest":{"type":"slide","state":"contents","slide":"none"},"url":{"native":"assets\/57D59BF8-900B-4C0A-9E93-9B19486BB94C.pdf"},"width":153,"height":153},"BFA9F5DBA1DB20E82B98AE4E5B9DC1CA":{"type":"texture","index":2,"assetRequest":{"type":"slide","state":"contents","slide":"none"},"url":{"native":"assets\/57D59BF8-900B-4C0A-9E93-9B19486BB94C.pdf"},"width":832,"height":41},"68E453E79F70E73A8CBC8132E316405C":{"type":"texture","index":9,"assetRequest":{"type":"slide","state":"contents","slide":"none"},"url":{"native":"assets\/57D59BF8-900B-4C0A-9E93-9B19486BB94C.pdf"},"width":1920,"height":1080}},"events":[{"effects":[{"beginTime":0,"baseLayer":{"animations":[],"initialState":{"affineTransform":[1,0,0,1,0,0],"masksToBounds":false,"rotation":0,"scale":1,"position":{"pointX":1343.4550893698909,"pointY":608.37721237460153},"width":153,"sublayerTransform":[1,0,0,0,0,1,0,0,0,0,1,0,0,0,0,1],"contentsRect":{"y":0,"x":0,"width":1,"height":1},"opacity":1,"edgeAntialiasingMask":251658240,"height":153,"hidden":false,"anchorPoint":{"pointX":0.5,"pointY":0.5}},"objectID":"DE4D66FD-0FDA-4BDA-962A-DAE2010670EF","layers":[{"animations":[],"initialState":{"affineTransform":[1,0,0,1,0,0],"masksToBounds":false,"rotation":0,"scale":1,"position":{"pointX":-306.95508936989086,"pointY":8.1227876253984732},"width":153,"sublayerTransform":[1,0,0,0,0,1,0,0,0,0,1,-0.00035007912466775983,0,0,0,1],"contentsRect":{"y":0,"x":0,"width":1,"height":1},"opacity":1,"edgeAntialiasingMask":251658240,"height":153,"hidden":false,"anchorPoint":{"pointX":-2.0062424141822932,"pointY":0.053090115198682834}},"layers":[{"animations":[{"additive":false,"timeOffset":0,"beginTime":1e-100,"repeatCount":0,"fillMode":"both","duration":1.25,"autoreverses":false,"animations":[{"repeatCount":0,"removedOnCompletion":true,"timingFunctions":[{"timingFunction":"custom","timingControlPoint1y":0,"timingControlPoint2x":0.70142078399658203,"timingControlPoint1x":0.30151674151420593,"timingControlPoint2y":1},{"timingFunction":"Linear"}],"keyTimes":[0,0.29999999999999999,0.5],"additive":false,"values":[{"transform":[1,0,0,0,0,1,0,0,0,0,1,0,0,0,0,1]},{"transform":[1,0,0,0,0,1,0,0,0,0,1,0,-15.300000000000001,0,0,1]},{"transform":[1,0,0,0,-0.15838444032453627,1,0,0,0,0,1,0,724.49140968482698,0,0,1]}],"timeOffset":0,"autoreverses":false,"property":"transform","fillMode":"forwards","duration":1.25,"beginTime":0},{"additive":false,"timeOffset":0,"beginTime":1.2499,"from":{"scalar":true},"repeatCount":0,"fillMode":"forwards","duration":0.0001,"autoreverses":false,"property":"hidden","to":{"scalar":true},"removedOnCompletion":true}],"removedOnCompletion":false}],"layers":[],"texturedRectangle":{"isBackgroundTexture":true,"singleTextureOpacity":1,"textureType":5,"textBaseline":0,"textXHeight":0,"isVerticalText":false},"initialState":{"affineTransform":[1,0,0,1,0,0],"masksToBounds":false,"rotation":0,"scale":1,"position":{"pointX":74.544910630109143,"pointY":74.622787625398473},"width":153,"sublayerTransform":[1,0,0,0,0,1,0,0,0,0,1,0,0,0,0,1],"contentsRect":{"y":0,"x":0,"width":1,"height":1},"opacity":1,"edgeAntialiasingMask":0,"height":153,"hidden":false,"anchorPoint":{"pointX":0.5,"pointY":0.5}},"texture":"304E32496D30F9D769E87A3F923D691F"}]}]},"effects":[],"duration":1.25,"type":"buildOut","attributes":{"direction":11},"name":"com.apple.iWork.Keynote.KNBuildSkid","objectID":"DE4D66FD-0FDA-4BDA-962A-DAE2010670EF"}],"automaticPlay":false,"hyperlinks":[],"accessibility":[{"text":"迄今为止，美国男子篮球队一直是奥运会上的统治者，多次夺得金牌，具有压倒性的优势。","targetRectangle":{"y":386.38504111766815,"x":191.54612731933594,"width":1440,"height":60.000002384185791}},{"text":"1936年柏林奥运会，篮球首次成为奥运会正式项目。","targetRectangle":{"y":215.01472198963165,"x":191.54612731933594,"width":852.046875,"height":62.514594750189474}},{"text":"pasted-image.png","targetRectangle":{"y":336.55415329257028,"x":1618.6601674948909,"width":149.74009423603457,"height":149.66716507134026}},{"text":"pasted-image.png","targetRectangle":{"y":531.87721237460153,"x":1266.9550893698909,"width":149.74009423603457,"height":149.66716507134026}},{"text":"同时，苏联、南斯拉夫、澳大利亚、巴西、西班牙等国家表现不俗。","targetRectangle":{"y":581.53851401805878,"x":191.54612731933594,"width":1080,"height":60.000002384185791}}],"baseLayer":{"animations":[],"initialState":{"affineTransform":[1,0,0,1,0,0],"masksToBounds":false,"rotation":0,"scale":1,"position":{"pointX":960,"pointY":540},"width":1920,"sublayerTransform":[1,0,0,0,0,1,0,0,0,0,1,0,0,0,0,1],"contentsRect":{"y":0,"x":0,"width":1,"height":1},"opacity":1,"edgeAntialiasingMask":251658240,"height":1080,"hidden":false,"anchorPoint":{"pointX":0.5,"pointY":0.5}},"layers":[{"animations":[],"initialState":{"affineTransform":[1,0,0,1,0,0],"masksToBounds":false,"rotation":0,"scale":1,"position":{"pointX":960,"pointY":540},"width":1920,"sublayerTransform":[1,0,0,0,0,1,0,0,0,0,1,0,0,0,0,1],"contentsRect":{"y":0,"x":0,"width":1,"height":1},"opacity":1,"edgeAntialiasingMask":251658240,"height":1080,"hidden":false,"anchorPoint":{"pointX":0.5,"pointY":0.5}},"layers":[{"animations":[],"initialState":{"affineTransform":[1,0,0,1,0,0],"masksToBounds":false,"rotation":0,"scale":1,"position":{"pointX":960,"pointY":540},"width":1920,"sublayerTransform":[1,0,0,0,0,1,0,0,0,0,1,0,0,0,0,1],"contentsRect":{"y":0,"x":0,"width":1,"height":1},"opacity":1,"edgeAntialiasingMask":251658240,"height":1080,"hidden":false,"anchorPoint":{"pointX":0.5,"pointY":0.5}},"layers":[{"animations":[],"layers":[],"texturedRectangle":{"isBackgroundTexture":true,"singleTextureOpacity":1,"textureType":1,"textBaseline":0,"textXHeight":0,"isVerticalText":false},"initialState":{"affineTransform":[1,0,0,1,0,0],"masksToBounds":false,"rotation":0,"scale":1,"position":{"pointX":960,"pointY":540},"width":1920,"sublayerTransform":[1,0,0,0,0,1,0,0,0,0,1,0,0,0,0,1],"contentsRect":{"y":0,"x":0,"width":1,"height":1},"opacity":1,"edgeAntialiasingMask":0,"height":1080,"hidden":false,"anchorPoint":{"pointX":0.5,"pointY":0.5}},"texture":"C25C25FF361FB24FC35F6B120D2F252D"}]}]},{"animations":[],"initialState":{"affineTransform":[1,0,0,1,0,0],"masksToBounds":false,"rotation":0,"scale":1,"position":{"pointX":960,"pointY":540},"width":1920,"sublayerTransform":[1,0,0,0,0,1,0,0,0,0,1,0,0,0,0,1],"contentsRect":{"y":0,"x":0,"width":1,"height":1},"opacity":1,"edgeAntialiasingMask":251658240,"height":1080,"hidden":false,"anchorPoint":{"pointX":0.5,"pointY":0.5}},"layers":[{"animations":[],"initialState":{"affineTransform":[1,0,0,1,0,0],"masksToBounds":false,"rotation":0,"scale":1,"position":{"pointX":666.32121276855469,"pointY":248.56246948242188},"width":1005,"sublayerTransform":[1,0,0,0,0,1,0,0,0,0,1,0,0,0,0,1],"contentsRect":{"y":0,"x":0,"width":1,"height":1},"opacity":1,"edgeAntialiasingMask":251658240,"height":115,"hidden":false,"anchorPoint":{"pointX":0.5,"pointY":0.5}},"layers":[{"animations":[],"layers":[],"texturedRectangle":{"singleTextureOpacity":1,"textXHeight":0,"shapePath":{"lineWidth":1,"flatness":0.59999999999999998,"lineCapStyle":0,"elements":[{"type":"MoveToPoint","points":[[84.254462768554674,7.062469482421875]]},{"type":"AddLine","points":[[920.96505017089839,7.062469482421875]]},{"type":"AddCurve","points":[[942.73217875404021,7.062469482421875],[955.7924559039252,7.062469482421875],[964.49930733718202,10.077838443126467]]},{"type":"AddCurve","points":[[978.38762990739474,15.132774462571405],[989.32799519074888,26.07313974592563],[994.38293121019387,39.961462316138437]]},{"type":"AddCurve","points":[[996.37779022609448,45.442292417320573],[997.39830017089844,51.22989191402695],[997.39830017089844,57.062469482421875]]},{"type":"AddCurve","points":[[997.39830017089844,62.895047050816828],[996.37779022609448,68.682646547523177],[994.38293121019387,74.163476648705341]]},{"type":"AddCurve","points":[[989.32799519074888,88.05179921891812],[978.38762990739474,98.992164502272317],[964.49930733718202,104.04710052171731]]},{"type":"AddCurve","points":[[955.7924559039252,107.06246948242188],[942.73217875404021,107.06246948242188],[920.96505017089839,107.06246948242188]]},{"type":"AddLine","points":[[84.254462768554674,107.06246948242188]]},{"type":"AddCurve","points":[[62.487334185412976,107.06246948242188],[49.427057035527923,107.06246948242188],[40.72020560227125,104.04710052171731]]},{"type":"AddCurve","points":[[26.831883032058442,98.992164502272374],[15.891517748704217,88.05179921891812],[10.836581729259279,74.163476648705341]]},{"type":"AddCurve","points":[[8.841722713358763,68.682646547523177],[7.8212127685546875,62.895047050816828],[7.8212127685546875,57.062469482421875]]},{"type":"AddCurve","points":[[7.8212127685546875,51.229891914026922],[8.8417227133587346,45.442292417320573],[10.836581729259251,39.961462316138437]]},{"type":"AddCurve","points":[[15.891517748704189,26.07313974592563],[26.831883032058471,15.132774462571376],[40.720205602271278,10.077838443126439]]},{"type":"AddCurve","points":[[49.427057035527952,7.062469482421875],[62.487334185412976,7.062469482421875],[84.254462768554674,7.062469482421875]]},{"type":"CloseSubpath"},{"type":"MoveToPoint","points":[[84.254462768554674,7.062469482421875]]}],"windingRule":0,"lineJoinStyle":0,"miterLimit":10},"isBackgroundTexture":true,"textBaseline":0,"isVerticalText":false,"textureType":5},"initialState":{"affineTransform":[1,0,0,1,0,0],"masksToBounds":false,"rotation":0,"scale":1,"position":{"pointX":494.67878723144531,"pointY":50.437530517578125},"width":1005,"sublayerTransform":[1,0,0,0,0,1,0,0,0,0,1,0,0,0,0,1],"contentsRect":{"y":0,"x":0,"width":1,"height":1},"opacity":1,"edgeAntialiasingMask":0,"height":115,"hidden":false,"anchorPoint":{"pointX":0.5,"pointY":0.5}},"texture":"769346EB9B7D226C18A37CD23110C7E0"}]}]},{"animations":[],"initialState":{"affineTransform":[1,0,0,1,0,0],"masksToBounds":false,"rotation":0,"scale":1,"position":{"pointX":960,"pointY":540},"width":1920,"sublayerTransform":[1,0,0,0,0,1,0,0,0,0,1,0,0,0,0,1],"contentsRect":{"y":0,"x":0,"width":1,"height":1},"opacity":1,"edgeAntialiasingMask":251658240,"height":1080,"hidden":false,"anchorPoint":{"pointX":0.5,"pointY":0.5}},"layers":[{"animations":[],"initialState":{"affineTransform":[1,0,0,1,0,0],"masksToBounds":false,"rotation":0,"scale":1,"position":{"pointX":603.54612731933594,"pointY":231.51472198963165},"width":832,"sublayerTransform":[1,0,0,0,0,1,0,0,0,0,1,0,0,0,0,1],"contentsRect":{"y":0,"x":0,"width":1,"height":1},"opacity":1,"edgeAntialiasingMask":251658240,"height":41,"hidden":false,"anchorPoint":{"pointX":0.5,"pointY":0.5}},"layers":[{"animations":[],"layers":[],"texturedRectangle":{"singleTextureOpacity":1,"textXHeight":0.46046112804878048,"textBaseline":0.77732172535686961,"isBackgroundTexture":true,"isVerticalText":false,"textColor":[0.99990898370742798,1,0.99987810850143433,1],"textureType":6},"initialState":{"affineTransform":[1,0,0,1,0,0],"masksToBounds":false,"rotation":0,"scale":1,"position":{"pointX":420.45387268066406,"pointY":32.485278010368347},"width":832,"sublayerTransform":[1,0,0,0,0,1,0,0,0,0,1,0,0,0,0,1],"contentsRect":{"y":0,"x":0,"width":1,"height":1},"opacity":1,"edgeAntialiasingMask":0,"height":41,"hidden":false,"anchorPoint":{"pointX":0.5,"pointY":0.5}},"texture":"BFA9F5DBA1DB20E82B98AE4E5B9DC1CA"}]}]},{"animations":[],"initialState":{"affineTransform":[1,0,0,1,0,0],"masksToBounds":false,"rotation":0,"scale":1,"position":{"pointX":960,"pointY":540},"width":1920,"sublayerTransform":[1,0,0,0,0,1,0,0,0,0,1,0,0,0,0,1],"contentsRect":{"y":0,"x":0,"width":1,"height":1},"opacity":1,"edgeAntialiasingMask":251658240,"height":1080,"hidden":false,"anchorPoint":{"pointX":0.5,"pointY":0.5}},"layers":[{"animations":[],"initialState":{"affineTransform":[1,0,0,1,0,0],"masksToBounds":false,"rotation":0,"scale":1,"position":{"pointX":952.39724731445312,"pointY":418.88504028320312},"width":1586,"sublayerTransform":[1,0,0,0,0,1,0,0,0,0,1,0,0,0,0,1],"contentsRect":{"y":0,"x":0,"width":1,"height":1},"opacity":1,"edgeAntialiasingMask":251658240,"height":115,"hidden":false,"anchorPoint":{"pointX":0.5,"pointY":0.5}},"layers":[{"animations":[],"layers":[],"texturedRectangle":{"singleTextureOpacity":1,"textXHeight":0,"shapePath":{"lineWidth":1,"flatness":0.59999999999999998,"lineCapStyle":0,"elements":[{"type":"MoveToPoint","points":[[83.830497314453112,7.385040283203125]]},{"type":"AddLine","points":[[1502.5340656738281,7.385040283203125]]},{"type":"AddCurve","points":[[1524.3011942569697,7.385040283203125],[1537.3614714068549,7.385040283203125],[1546.0683228401115,10.400409243907689]]},{"type":"AddCurve","points":[[1559.9566454103242,15.455345263352683],[1570.8970106936786,26.39571054670688],[1575.9519467131236,40.284033116919716]]},{"type":"AddCurve","points":[[1577.9468057290242,45.764863218101823],[1578.9673156738281,51.5524627148082],[1578.9673156738281,57.385040283203125]]},{"type":"AddCurve","points":[[1578.9673156738281,63.217617851598106],[1577.9468057290242,69.005217348304427],[1575.9519467131236,74.486047449486591]]},{"type":"AddCurve","points":[[1570.8970106936786,88.37437001969937],[1559.9566454103242,99.314735303053567],[1546.0683228401115,104.36967132249856]]},{"type":"AddCurve","points":[[1537.3614714068549,107.38504028320312],[1524.3011942569697,107.38504028320312],[1502.5340656738281,107.38504028320312]]},{"type":"AddLine","points":[[83.830497314453112,107.38504028320312]]},{"type":"AddCurve","points":[[62.063368731311414,107.38504028320312],[49.003091581426361,107.38504028320312],[40.296240148169687,104.36967132249856]]},{"type":"AddCurve","points":[[26.40791757795688,99.314735303053624],[15.467552294602655,88.37437001969937],[10.412616275157717,74.486047449486591]]},{"type":"AddCurve","points":[[8.4177572592572005,69.005217348304427],[7.397247314453125,63.21761785159805],[7.397247314453125,57.385040283203125]]},{"type":"AddCurve","points":[[7.397247314453125,51.5524627148082],[8.4177572592571721,45.764863218101823],[10.412616275157689,40.284033116919659]]},{"type":"AddCurve","points":[[15.467552294602626,26.39571054670688],[26.407917577956908,15.455345263352626],[40.296240148169716,10.400409243907689]]},{"type":"AddCurve","points":[[49.003091581426389,7.385040283203125],[62.063368731311414,7.385040283203125],[83.830497314453112,7.385040283203125]]},{"type":"CloseSubpath"},{"type":"MoveToPoint","points":[[83.830497314453112,7.385040283203125]]}],"windingRule":0,"lineJoinStyle":0,"miterLimit":10},"isBackgroundTexture":true,"textBaseline":0,"isVerticalText":false,"textureType":5},"initialState":{"affineTransform":[1,0,0,1,0,0],"masksToBounds":false,"rotation":0,"scale":1,"position":{"pointX":785.60275268554688,"pointY":50.114959716796875},"width":1586,"sublayerTransform":[1,0,0,0,0,1,0,0,0,0,1,0,0,0,0,1],"contentsRect":{"y":0,"x":0,"width":1,"height":1},"opacity":1,"edgeAntialiasingMask":0,"height":115,"hidden":false,"anchorPoint":{"pointX":0.5,"pointY":0.5}},"texture":"D30DCBD739CF9BA010D281948BDF9250"}]}]},{"animations":[],"initialState":{"affineTransform":[1,0,0,1,0,0],"masksToBounds":false,"rotation":0,"scale":1,"position":{"pointX":960,"pointY":540},"width":1920,"sublayerTransform":[1,0,0,0,0,1,0,0,0,0,1,0,0,0,0,1],"contentsRect":{"y":0,"x":0,"width":1,"height":1},"opacity":1,"edgeAntialiasingMask":251658240,"height":1080,"hidden":false,"anchorPoint":{"pointX":0.5,"pointY":0.5}},"layers":[{"animations":[],"initialState":{"affineTransform":[1,0,0,1,0,0],"masksToBounds":false,"rotation":0,"scale":1,"position":{"pointX":1695.1601674948909,"pointY":413.05415329257028},"width":153,"sublayerTransform":[1,0,0,0,0,1,0,0,0,0,1,0,0,0,0,1],"contentsRect":{"y":0,"x":0,"width":1,"height":1},"opacity":1,"edgeAntialiasingMask":251658240,"height":153,"hidden":false,"anchorPoint":{"pointX":0.5,"pointY":0.5}},"layers":[{"animations":[],"layers":[],"texturedRectangle":{"isBackgroundTexture":true,"singleTextureOpacity":1,"textureType":5,"textBaseline":0,"textXHeight":0,"isVerticalText":false},"initialState":{"affineTransform":[1,0,0,1,0,0],"masksToBounds":false,"rotation":0,"scale":1,"position":{"pointX":74.839832505109143,"pointY":74.945846707429723},"width":153,"sublayerTransform":[1,0,0,0,0,1,0,0,0,0,1,0,0,0,0,1],"contentsRect":{"y":0,"x":0,"width":1,"height":1},"opacity":1,"edgeAntialiasingMask":0,"height":153,"hidden":false,"anchorPoint":{"pointX":0.5,"pointY":0.5}},"texture":"1E00397D677FE47D00B9009AE78DD3DF"}]}]},{"animations":[],"initialState":{"affineTransform":[1,0,0,1,0,0],"masksToBounds":false,"rotation":0,"scale":1,"position":{"pointX":960,"pointY":540},"width":1920,"sublayerTransform":[1,0,0,0,0,1,0,0,0,0,1,0,0,0,0,1],"contentsRect":{"y":0,"x":0,"width":1,"height":1},"opacity":1,"edgeAntialiasingMask":251658240,"height":1080,"hidden":false,"anchorPoint":{"pointX":0.5,"pointY":0.5}},"layers":[{"animations":[],"initialState":{"affineTransform":[1,0,0,1,0,0],"masksToBounds":false,"rotation":0,"scale":1,"position":{"pointX":898.04612731933594,"pointY":402.88504111766815},"width":1421,"sublayerTransform":[1,0,0,0,0,1,0,0,0,0,1,0,0,0,0,1],"contentsRect":{"y":0,"x":0,"width":1,"height":1},"opacity":1,"edgeAntialiasingMask":251658240,"height":41,"hidden":false,"anchorPoint":{"pointX":0.5,"pointY":0.5}},"layers":[{"animations":[],"layers":[],"texturedRectangle":{"singleTextureOpacity":1,"textXHeight":0.52682926829268284,"textBaseline":0.78402478811217513,"isBackgroundTexture":true,"isVerticalText":false,"textColor":[0.99990898370742798,1,0.99987810850143433,1],"textureType":6},"initialState":{"affineTransform":[1,0,0,1,0,0],"masksToBounds":false,"rotation":0,"scale":1,"position":{"pointX":713.95387268066406,"pointY":30.114958882331848},"width":1421,"sublayerTransform":[1,0,0,0,0,1,0,0,0,0,1,0,0,0,0,1],"contentsRect":{"y":0,"x":0,"width":1,"height":1},"opacity":1,"edgeAntialiasingMask":0,"height":41,"hidden":false,"anchorPoint":{"pointX":0.5,"pointY":0.5}},"texture":"672EE0C5DB726A7305A298BBDB9D6824"}]}]},{"animations":[],"initialState":{"affineTransform":[1,0,0,1,0,0],"masksToBounds":false,"rotation":0,"scale":1,"position":{"pointX":960,"pointY":540},"width":1920,"sublayerTransform":[1,0,0,0,0,1,0,0,0,0,1,0,0,0,0,1],"contentsRect":{"y":0,"x":0,"width":1,"height":1},"opacity":1,"edgeAntialiasingMask":251658240,"height":1080,"hidden":false,"anchorPoint":{"pointX":0.5,"pointY":0.5}},"layers":[{"animations":[],"initialState":{"affineTransform":[1,0,0,1,0,0],"masksToBounds":false,"rotation":0,"scale":1,"position":{"pointX":755.76130676269531,"pointY":614.03851318359375},"width":1206,"sublayerTransform":[1,0,0,0,0,1,0,0,0,0,1,0,0,0,0,1],"contentsRect":{"y":0,"x":0,"width":1,"height":1},"opacity":1,"edgeAntialiasingMask":251658240,"height":115,"hidden":false,"anchorPoint":{"pointX":0.5,"pointY":0.5}},"layers":[{"animations":[],"layers":[],"texturedRectangle":{"singleTextureOpacity":1,"textXHeight":0,"shapePath":{"lineWidth":1,"flatness":0.59999999999999998,"lineCapStyle":0,"elements":[{"type":"MoveToPoint","points":[[84.194556762695299,7.53851318359375]]},{"type":"AddLine","points":[[1122.0311817626953,7.53851318359375]]},{"type":"AddCurve","points":[[1143.7983103458369,7.53851318359375],[1156.8585874957221,7.53851318359375],[1165.5654389289787,10.553882144298314]]},{"type":"AddCurve","points":[[1179.4537614991914,15.608818163743308],[1190.3941267825458,26.549183447097562],[1195.4490628019907,40.437506017310284]]},{"type":"AddCurve","points":[[1197.4439218178914,45.918336118492448],[1198.4644317626953,51.705935615198882],[1198.4644317626953,57.53851318359375]]},{"type":"AddCurve","points":[[1198.4644317626953,63.371090751988731],[1197.4439218178914,69.158690248695052],[1195.4490628019907,74.639520349877216]]},{"type":"AddCurve","points":[[1190.3941267825458,88.527842920090052],[1179.4537614991914,99.468208203444192],[1165.5654389289787,104.52314422288919]]},{"type":"AddCurve","points":[[1156.8585874957221,107.53851318359375],[1143.7983103458369,107.53851318359375],[1122.0311817626953,107.53851318359375]]},{"type":"AddLine","points":[[84.194556762695299,107.53851318359375]]},{"type":"AddCurve","points":[[62.427428179553601,107.53851318359375],[49.367151029668548,107.53851318359375],[40.660299596411875,104.52314422288919]]},{"type":"AddCurve","points":[[26.771977026199067,99.468208203444192],[15.831611742844842,88.527842920090052],[10.776675723399904,74.639520349877216]]},{"type":"AddCurve","points":[[8.781816707499388,69.158690248695052],[7.7613067626953125,63.371090751988731],[7.7613067626953125,57.53851318359375]]},{"type":"AddCurve","points":[[7.7613067626953125,51.705935615198769],[8.7818167074993596,45.918336118492448],[10.776675723399876,40.437506017310284]]},{"type":"AddCurve","points":[[15.831611742844814,26.549183447097562],[26.771977026199096,15.608818163743308],[40.660299596411903,10.553882144298314]]},{"type":"AddCurve","points":[[49.367151029668577,7.53851318359375],[62.427428179553601,7.53851318359375],[84.194556762695299,7.53851318359375]]},{"type":"CloseSubpath"},{"type":"MoveToPoint","points":[[84.194556762695299,7.53851318359375]]}],"windingRule":0,"lineJoinStyle":0,"miterLimit":10},"isBackgroundTexture":true,"textBaseline":0,"isVerticalText":false,"textureType":5},"initialState":{"affineTransform":[1,0,0,1,0,0],"masksToBounds":false,"rotation":0,"scale":1,"position":{"pointX":595.23869323730469,"pointY":49.96148681640625},"width":1206,"sublayerTransform":[1,0,0,0,0,1,0,0,0,0,1,0,0,0,0,1],"contentsRect":{"y":0,"x":0,"width":1,"height":1},"opacity":1,"edgeAntialiasingMask":0,"height":115,"hidden":false,"anchorPoint":{"pointX":0.5,"pointY":0.5}},"texture":"17D5F579A7EEF91B82F8F0BDFB2BB53B"}]}]},{"animations":[],"initialState":{"affineTransform":[1,0,0,1,0,0],"masksToBounds":false,"rotation":0,"scale":1,"position":{"pointX":960,"pointY":540},"width":1920,"sublayerTransform":[1,0,0,0,0,1,0,0,0,0,1,0,0,0,0,1],"contentsRect":{"y":0,"x":0,"width":1,"height":1},"opacity":1,"edgeAntialiasingMask":251658240,"height":1080,"hidden":false,"anchorPoint":{"pointX":0.5,"pointY":0.5}},"layers":[{"animations":[],"initialState":{"affineTransform":[1,0,0,1,0,0],"masksToBounds":false,"rotation":0,"scale":1,"position":{"pointX":1343.4550893698909,"pointY":608.37721237460153},"width":153,"sublayerTransform":[1,0,0,0,0,1,0,0,0,0,1,0,0,0,0,1],"contentsRect":{"y":0,"x":0,"width":1,"height":1},"opacity":1,"edgeAntialiasingMask":251658240,"height":153,"hidden":false,"anchorPoint":{"pointX":0.5,"pointY":0.5}},"objectID":"DE4D66FD-0FDA-4BDA-962A-DAE2010670EF","layers":[{"animations":[],"layers":[],"texturedRectangle":{"isBackgroundTexture":true,"singleTextureOpacity":1,"textureType":5,"textBaseline":0,"textXHeight":0,"isVerticalText":false},"initialState":{"affineTransform":[1,0,0,1,0,0],"masksToBounds":false,"rotation":0,"scale":1,"position":{"pointX":74.544910630109143,"pointY":74.622787625398473},"width":153,"sublayerTransform":[1,0,0,0,0,1,0,0,0,0,1,0,0,0,0,1],"contentsRect":{"y":0,"x":0,"width":1,"height":1},"opacity":1,"edgeAntialiasingMask":0,"height":153,"hidden":false,"anchorPoint":{"pointX":0.5,"pointY":0.5}},"texture":"304E32496D30F9D769E87A3F923D691F"}]}]},{"animations":[],"initialState":{"affineTransform":[1,0,0,1,0,0],"masksToBounds":false,"rotation":0,"scale":1,"position":{"pointX":960,"pointY":540},"width":1920,"sublayerTransform":[1,0,0,0,0,1,0,0,0,0,1,0,0,0,0,1],"contentsRect":{"y":0,"x":0,"width":1,"height":1},"opacity":1,"edgeAntialiasingMask":251658240,"height":1080,"hidden":false,"anchorPoint":{"pointX":0.5,"pointY":0.5}},"layers":[{"animations":[],"initialState":{"affineTransform":[1,0,0,1,0,0],"masksToBounds":false,"rotation":0,"scale":1,"position":{"pointX":717.04612731933594,"pointY":598.03851401805878},"width":1059,"sublayerTransform":[1,0,0,0,0,1,0,0,0,0,1,0,0,0,0,1],"contentsRect":{"y":0,"x":0,"width":1,"height":1},"opacity":1,"edgeAntialiasingMask":251658240,"height":41,"hidden":false,"anchorPoint":{"pointX":0.5,"pointY":0.5}},"layers":[{"animations":[],"layers":[],"texturedRectangle":{"singleTextureOpacity":1,"textXHeight":0.52682926829268284,"textBaseline":0.78776802958511727,"isBackgroundTexture":true,"isVerticalText":false,"textColor":[0.99990898370742798,1,0.99987810850143433,1],"textureType":6},"initialState":{"affineTransform":[1,0,0,1,0,0],"masksToBounds":false,"rotation":0,"scale":1,"position":{"pointX":534.95387268066406,"pointY":29.961485981941223},"width":1059,"sublayerTransform":[1,0,0,0,0,1,0,0,0,0,1,0,0,0,0,1],"contentsRect":{"y":0,"x":0,"width":1,"height":1},"opacity":1,"edgeAntialiasingMask":0,"height":41,"hidden":false,"anchorPoint":{"pointX":0.5,"pointY":0.5}},"texture":"73746CC77F98038CCDD6A664DF9DC261"}]}]}]}},{"effects":[{"beginTime":0,"baseLayer":{"animations":[],"initialState":{"affineTransform":[1,0,0,1,0,0],"masksToBounds":false,"rotation":0,"scale":1,"position":{"pointX":960,"pointY":540},"width":1920,"sublayerTransform":[1,0,0,0,0,1,0,0,0,0,1,0,0,0,0,1],"contentsRect":{"y":0,"x":0,"width":1,"height":1},"opacity":1,"edgeAntialiasingMask":251658240,"height":1080,"hidden":false,"anchorPoint":{"pointX":0.5,"pointY":0.5}},"objectID":"0","layers":[{"animations":[],"initialState":{"affineTransform":[1,0,0,1,0,0],"masksToBounds":false,"rotation":0,"scale":1,"position":{"pointX":960,"pointY":540},"width":1920,"sublayerTransform":[1,0,0,0,0,1,0,0,0,0,1,-0.00035007912466775983,0,0,0,1],"contentsRect":{"y":0,"x":0,"width":1,"height":1},"opacity":1,"edgeAntialiasingMask":251658240,"height":1080,"hidden":false,"anchorPoint":{"pointX":0.5,"pointY":0.5}},"layers":[{"animations":[],"layers":[],"texturedRectangle":{"isBackgroundTexture":false,"singleTextureOpacity":1,"textureType":0,"textBaseline":0,"textXHeight":0,"isVerticalText":false},"initialState":{"affineTransform":[1,0,0,1,0,0],"masksToBounds":false,"rotation":0,"scale":1,"position":{"pointX":960,"pointY":540},"width":1920,"sublayerTransform":[1,0,0,0,0,1,0,0,0,0,1,0,0,0,0,1],"contentsRect":{"y":0,"x":0,"width":1,"height":1},"opacity":1,"edgeAntialiasingMask":0,"height":1080,"hidden":false,"anchorPoint":{"pointX":0.5,"pointY":0.5}},"texture":"C25C25FF361FB24FC35F6B120D2F252D"},{"animations":[{"repeatCount":0,"removedOnCompletion":false,"from":{"scalar":1},"timingFunction":"EaseInEaseOut","additive":false,"timeOffset":0,"autoreverses":false,"property":"opacity","fillMode":"both","duration":0.5,"beginTime":0,"to":{"scalar":0}}],"layers":[],"texturedRectangle":{"isBackgroundTexture":false,"singleTextureOpacity":1,"textureType":0,"textBaseline":0,"textXHeight":0,"isVerticalText":false},"initialState":{"affineTransform":[1,0,0,1,0,0],"masksToBounds":false,"rotation":0,"scale":1,"position":{"pointX":960,"pointY":540},"width":1920,"sublayerTransform":[1,0,0,0,0,1,0,0,0,0,1,0,0,0,0,1],"contentsRect":{"y":0,"x":0,"width":1,"height":1},"opacity":1,"edgeAntialiasingMask":0,"height":1080,"hidden":false,"anchorPoint":{"pointX":0.5,"pointY":0.5}},"texture":"68E453E79F70E73A8CBC8132E316405C"}]}]},"effects":[],"duration":0.5,"type":"transition","attributes":{"direction":11},"name":"apple:wipe","objectID":"0"}],"automaticPlay":false,"hyperlinks":[],"accessibility":[{"text":"迄今为止，美国男子篮球队一直是奥运会上的统治者，多次夺得金牌，具有压倒性的优势。","targetRectangle":{"y":386.38504111766815,"x":191.54612731933594,"width":1440,"height":60.000002384185791}},{"text":"1936年柏林奥运会，篮球首次成为奥运会正式项目。","targetRectangle":{"y":215.01472198963165,"x":191.54612731933594,"width":852.046875,"height":62.514594750189474}},{"text":"pasted-image.png","targetRectangle":{"y":336.55415329257028,"x":1618.6601674948909,"width":149.74009423603457,"height":149.66716507134026}},{"text":"同时，苏联、南斯拉夫、澳大利亚、巴西、西班牙等国家表现不俗。","targetRectangle":{"y":581.53851401805878,"x":191.54612731933594,"width":1080,"height":60.000002384185791}}],"baseLayer":{"animations":[],"initialState":{"affineTransform":[1,0,0,1,0,0],"masksToBounds":false,"rotation":0,"scale":1,"position":{"pointX":960,"pointY":540},"width":1920,"sublayerTransform":[1,0,0,0,0,1,0,0,0,0,1,0,0,0,0,1],"contentsRect":{"y":0,"x":0,"width":1,"height":1},"opacity":1,"edgeAntialiasingMask":251658240,"height":1080,"hidden":false,"anchorPoint":{"pointX":0.5,"pointY":0.5}},"objectID":"0","layers":[{"animations":[],"initialState":{"affineTransform":[1,0,0,1,0,0],"masksToBounds":false,"rotation":0,"scale":1,"position":{"pointX":960,"pointY":540},"width":1920,"sublayerTransform":[1,0,0,0,0,1,0,0,0,0,1,-0.00035007912466775983,0,0,0,1],"contentsRect":{"y":0,"x":0,"width":1,"height":1},"opacity":1,"edgeAntialiasingMask":251658240,"height":1080,"hidden":false,"anchorPoint":{"pointX":0.5,"pointY":0.5}},"layers":[{"animations":[],"layers":[],"texturedRectangle":{"isBackgroundTexture":false,"singleTextureOpacity":1,"textureType":0,"textBaseline":0,"textXHeight":0,"isVerticalText":false},"initialState":{"affineTransform":[1,0,0,1,0,0],"masksToBounds":false,"rotation":0,"scale":1,"position":{"pointX":960,"pointY":540},"width":1920,"sublayerTransform":[1,0,0,0,0,1,0,0,0,0,1,0,0,0,0,1],"contentsRect":{"y":0,"x":0,"width":1,"height":1},"opacity":1,"edgeAntialiasingMask":0,"height":1080,"hidden":false,"anchorPoint":{"pointX":0.5,"pointY":0.5}},"texture":"68E453E79F70E73A8CBC8132E316405C"}]}]}}]}